{
    "5.1 Koşullu İfadeler": {
            "Veri gelmeli" : "Veri gelmeli"
    },
    "5.2 İç İçe Koşul İfadeleri":{
            "Veri gelmeli" : "Veri gelmeli"
    },
    "5.3 Mantıksal İfadeler ve Bağlaçlar": {
            "Veri gelmeli" : "Veri gelmeli"
    },
    "5.4 Python Blok Yapısı": {
            "Veri gelmeli" : "Veri gelmeli"
    },
    "5.5 if yapısı": {
            "Veri gelmeli" : "Veri gelmeli"
    },
    "5.6 if-else Yapısı": {
            "Veri gelmeli" : "Veri gelmeli"
    },
    "5.7 if-elif-else Yapısı": {
            "Veri gelmeli" : "Veri gelmeli"
    }
}